README.md
setup.cfg
setup.py
credit_scoring/__init__.py
credit_scoring.egg-info/PKG-INFO
credit_scoring.egg-info/SOURCES.txt
credit_scoring.egg-info/dependency_links.txt
credit_scoring.egg-info/requires.txt
credit_scoring.egg-info/top_level.txt
credit_scoring/metrics/__init__.py
credit_scoring/metrics/_ks.py
credit_scoring/metrics/_lift.py
credit_scoring/metrics/_roc_auc.py
credit_scoring/metrics/credit_score.py
credit_scoring/woe/__init__.py
credit_scoring/woe/_woe_transform.py