Metadata-Version: 1.1
Name: credit-scoring
Version: 0.1.0
Summary: This library help researcher have quick result with woe, iv, result reporting with credit scoring problem
Home-page: https://github.com/minhtcuet/creditscoring
Author: Minh Tran
Author-email: minhtc.uet@gmail.com
License: MIT
Download-URL: https://github.com/minhtcuet/creditscoring/archive/v_01.tar.gz
Keywords: Credit,Credit Score,WOE,IV,WOE-IV,GINI,KS,Lift,GAIN
Platform: UNKNOWN
Classifier: Development Status :: 3 - Alpha
Classifier: Intended Audience :: Developers
Classifier: Topic :: Software Development :: Build Tools
Classifier: License :: OSI Approved :: MIT License
Classifier: Programming Language :: Python :: 3
Classifier: Programming Language :: Python :: 3.4
Classifier: Programming Language :: Python :: 3.5
Classifier: Programming Language :: Python :: 3.6
Classifier: Programming Language :: Python :: 3.7
Classifier: Programming Language :: Python :: 3.8
Classifier: Programming Language :: Python :: 3.9
